[
    {
        "SongID": 27,
        "Position": 52
    },
    {
        "SongID": 97,
        "Position": 98
    },
    {
        "SongID": 113,
        "Position": 43
    },
    {
        "SongID": 2670,
        "Position": 62
    },
    {
        "SongID": 5430,
        "Position": 91
    },
    {
        "SongID": 6082,
        "Position": 88
    },
    {
        "SongID": 7676,
        "Position": 79
    },
    {
        "SongID": 9713,
        "Position": 93
    },
    {
        "SongID": 12447,
        "Position": 44
    },
    {
        "SongID": 12451,
        "Position": 26
    },
    {
        "SongID": 12453,
        "Position": 51
    },
    {
        "SongID": 12454,
        "Position": 76
    },
    {
        "SongID": 12514,
        "Position": 55
    },
    {
        "SongID": 12521,
        "Position": 61
    },
    {
        "SongID": 12715,
        "Position": 75
    },
    {
        "SongID": 12959,
        "Position": 72
    },
    {
        "SongID": 13521,
        "Position": 77
    },
    {
        "SongID": 18935,
        "Position": 95
    },
    {
        "SongID": 18937,
        "Position": 65
    },
    {
        "SongID": 20411,
        "Position": 82
    },
    {
        "SongID": 20412,
        "Position": 34
    },
    {
        "SongID": 21968,
        "Position": 81
    },
    {
        "SongID": 25192,
        "Position": 83
    },
    {
        "SongID": 26553,
        "Position": 84
    },
    {
        "SongID": 26556,
        "Position": 73
    },
    {
        "SongID": 28181,
        "Position": 49
    },
    {
        "SongID": 66075,
        "Position": 92
    },
    {
        "SongID": 111044,
        "Position": 94
    },
    {
        "SongID": 118613,
        "Position": 78
    },
    {
        "SongID": 208657,
        "Position": 59
    },
    {
        "SongID": 501280,
        "Position": 29
    },
    {
        "SongID": 501282,
        "Position": 90
    },
    {
        "SongID": 501288,
        "Position": 17
    },
    {
        "SongID": 501328,
        "Position": 38
    },
    {
        "SongID": 501679,
        "Position": 50
    },
    {
        "SongID": 501680,
        "Position": 96
    },
    {
        "SongID": 501691,
        "Position": 22
    },
    {
        "SongID": 503972,
        "Position": 58
    },
    {
        "SongID": 531739,
        "Position": 28
    },
    {
        "SongID": 538737,
        "Position": 48
    },
    {
        "SongID": 539950,
        "Position": 100
    },
    {
        "SongID": 559564,
        "Position": 24
    },
    {
        "SongID": 600127,
        "Position": 23
    },
    {
        "SongID": 600128,
        "Position": 36
    },
    {
        "SongID": 600185,
        "Position": 71
    },
    {
        "SongID": 600205,
        "Position": 66
    },
    {
        "SongID": 600472,
        "Position": 47
    },
    {
        "SongID": 600502,
        "Position": 97
    },
    {
        "SongID": 600831,
        "Position": 12
    },
    {
        "SongID": 600832,
        "Position": 25
    },
    {
        "SongID": 601133,
        "Position": 5
    },
    {
        "SongID": 601134,
        "Position": 7
    },
    {
        "SongID": 601135,
        "Position": 1
    },
    {
        "SongID": 601136,
        "Position": 4
    },
    {
        "SongID": 601137,
        "Position": 2
    },
    {
        "SongID": 601138,
        "Position": 9
    },
    {
        "SongID": 601139,
        "Position": 6
    },
    {
        "SongID": 601140,
        "Position": 13
    },
    {
        "SongID": 601141,
        "Position": 11
    },
    {
        "SongID": 601142,
        "Position": 15
    },
    {
        "SongID": 601143,
        "Position": 14
    },
    {
        "SongID": 601144,
        "Position": 19
    },
    {
        "SongID": 601145,
        "Position": 89
    },
    {
        "SongID": 601406,
        "Position": 18
    },
    {
        "SongID": 601407,
        "Position": 39
    },
    {
        "SongID": 601408,
        "Position": 31
    },
    {
        "SongID": 601409,
        "Position": 40
    },
    {
        "SongID": 601410,
        "Position": 46
    },
    {
        "SongID": 601411,
        "Position": 53
    },
    {
        "SongID": 601495,
        "Position": 42
    },
    {
        "SongID": 601496,
        "Position": 41
    },
    {
        "SongID": 601497,
        "Position": 60
    },
    {
        "SongID": 601498,
        "Position": 74
    },
    {
        "SongID": 601499,
        "Position": 63
    },
    {
        "SongID": 601500,
        "Position": 68
    },
    {
        "SongID": 601501,
        "Position": 80
    },
    {
        "SongID": 601576,
        "Position": 35
    },
    {
        "SongID": 603673,
        "Position": 69
    },
    {
        "SongID": 605705,
        "Position": 3
    },
    {
        "SongID": 605706,
        "Position": 10
    },
    {
        "SongID": 605707,
        "Position": 8
    },
    {
        "SongID": 605708,
        "Position": 20
    },
    {
        "SongID": 605709,
        "Position": 33
    },
    {
        "SongID": 605710,
        "Position": 27
    },
    {
        "SongID": 605711,
        "Position": 21
    },
    {
        "SongID": 605712,
        "Position": 16
    },
    {
        "SongID": 605713,
        "Position": 32
    },
    {
        "SongID": 605714,
        "Position": 37
    },
    {
        "SongID": 605715,
        "Position": 30
    },
    {
        "SongID": 605716,
        "Position": 45
    },
    {
        "SongID": 611264,
        "Position": 70
    },
    {
        "SongID": 611265,
        "Position": 54
    },
    {
        "SongID": 611266,
        "Position": 56
    },
    {
        "SongID": 611267,
        "Position": 87
    },
    {
        "SongID": 611268,
        "Position": 57
    },
    {
        "SongID": 611269,
        "Position": 85
    },
    {
        "SongID": 611270,
        "Position": 86
    },
    {
        "SongID": 611271,
        "Position": 99
    },
    {
        "SongID": 611327,
        "Position": 67
    },
    {
        "SongID": 612766,
        "Position": 64
    }
]