[
    {
        "Position": "1",
        "Title": "Où aller",
        "Artist": "GIMS"
    },
    {
        "Position": "2",
        "Title": "4 Kampé",
        "Artist": "Joé Dwèt Filé"
    },
    {
        "Position": "3",
        "Title": "La vie qu'on mène",
        "Artist": "Ninho"
    },
    {
        "Position": "4",
        "Title": "Marlène",
        "Artist": "Fally Ipupa"
    },
    {
        "Position": "5",
        "Title": "I love you",
        "Artist": "Dadju & Tayc"
    },
    {
        "Position": "6",
        "Title": "Work (feat. Drake)",
        "Artist": "Rihanna"
    },
    {
        "Position": "7",
        "Title": "SOIS PAS TIMIDE",
        "Artist": "GIMS"
    },
    {
        "Position": "8",
        "Title": "Awuke",
        "Artist": "Davido & YG Marley"
    },
    {
        "Position": "9",
        "Title": "HEIS",
        "Artist": "Rema"
    },
    {
        "Position": "10",
        "Title": "SPIDER",
        "Artist": "GIMS & DYSTINCT"
    },
    {
        "Position": "11",
        "Title": "Jëli (feat. Wally B. Seck)",
        "Artist": "AMADEUS"
    },
    {
        "Position": "12",
        "Title": "Alliance",
        "Artist": "Fally Ipupa"
    },
    {
        "Position": "13",
        "Title": "OZEBA",
        "Artist": "Rema"
    },
    {
        "Position": "14",
        "Title": "Uranus",
        "Artist": "PNL"
    },
    {
        "Position": "15",
        "Title": "Love Nwantiti (ah ah ah) [feat. Joeboy & Kuami Eugene] [Remix]",
        "Artist": "CKay"
    },
    {
        "Position": "16",
        "Title": "Malouf Aloyoon",
        "Artist": "MarSimba"
    },
    {
        "Position": "17",
        "Title": "Mayday",
        "Artist": "Fally Ipupa"
    },
    {
        "Position": "18",
        "Title": "Terminal 2F",
        "Artist": "GIMS & Dadju"
    },
    {
        "Position": "19",
        "Title": "Pour Me Water",
        "Artist": "Kizz Daniel"
    },
    {
        "Position": "20",
        "Title": "Minimum ça",
        "Artist": "Dr. Yaro"
    },
    {
        "Position": "21",
        "Title": "Fais-le",
        "Artist": "Driks"
    },
    {
        "Position": "22",
        "Title": "Picsou",
        "Artist": "Dadju & Gazo"
    },
    {
        "Position": "23",
        "Title": "Coup du marteau (feat. Team Paiya, Ste Milano, Renard Barakissa, Tazeboy & PSK)",
        "Artist": "Tam Sir"
    },
    {
        "Position": "24",
        "Title": "Jamais",
        "Artist": "Gradur"
    },
    {
        "Position": "25",
        "Title": "DA",
        "Artist": "PNL"
    },
    {
        "Position": "26",
        "Title": "Feel Good",
        "Artist": "MohBad"
    },
    {
        "Position": "27",
        "Title": "Diwa Kae (feat. Kabza De Small, Young Stunna, Mkeyz, Mckenzie & Mthunzi)",
        "Artist": "De Mthuda"
    },
    {
        "Position": "28",
        "Title": "WAP (feat. Megan Thee Stallion)",
        "Artist": "Cardi B"
    },
    {
        "Position": "29",
        "Title": "Mira",
        "Artist": "PNL"
    },
    {
        "Position": "30",
        "Title": "Don't Judge Me",
        "Artist": "Chris Brown"
    },
    {
        "Position": "31",
        "Title": "Paris",
        "Artist": "King Promise"
    },
    {
        "Position": "32",
        "Title": "Sheita",
        "Artist": "PNL"
    },
    {
        "Position": "33",
        "Title": "Doggy",
        "Artist": "Aya Nakamura"
    },
    {
        "Position": "34",
        "Title": "Memories",
        "Artist": "Maroon 5"
    },
    {
        "Position": "35",
        "Title": "Lonely At The Top",
        "Artist": "Asake"
    },
    {
        "Position": "36",
        "Title": "Intentions (feat. Quavo)",
        "Artist": "Justin Bieber"
    },
    {
        "Position": "37",
        "Title": "Girls Want Girls (feat. Lil Baby)",
        "Artist": "Drake"
    },
    {
        "Position": "38",
        "Title": "Position",
        "Artist": "Franglish"
    },
    {
        "Position": "39",
        "Title": "YAYO",
        "Artist": "Rema"
    },
    {
        "Position": "40",
        "Title": "Dans la légende",
        "Artist": "PNL"
    },
    {
        "Position": "41",
        "Title": "Last Last",
        "Artist": "Burna Boy"
    },
    {
        "Position": "42",
        "Title": "Halali",
        "Artist": "MZIKA MIX"
    },
    {
        "Position": "43",
        "Title": "Bob Marley",
        "Artist": "Dadju"
    },
    {
        "Position": "44",
        "Title": "cœur Amoureux",
        "Artist": "Fally Ipupa"
    },
    {
        "Position": "45",
        "Title": "Awolowo (Remix)",
        "Artist": "Fido & Tiwa Savage"
    },
    {
        "Position": "46",
        "Title": "Grand bain (feat. Ninho)",
        "Artist": "Dadju"
    },
    {
        "Position": "47",
        "Title": "AZAMAN",
        "Artist": "Rema"
    },
    {
        "Position": "48",
        "Title": "You",
        "Artist": "Crayon & Young Jonn"
    },
    {
        "Position": "49",
        "Title": "Pariwo",
        "Artist": "MohBad & Bella Shmurda"
    },
    {
        "Position": "50",
        "Title": "J'me tire",
        "Artist": "GIMS"
    },
    {
        "Position": "51",
        "Title": "Ghost",
        "Artist": "Justin Bieber"
    },
    {
        "Position": "52",
        "Title": "Truc en plus / Hold You (Medley)",
        "Artist": "Jeady Jay"
    },
    {
        "Position": "53",
        "Title": "HEHEHE",
        "Artist": "Rema"
    },
    {
        "Position": "54",
        "Title": "La vie est belle",
        "Artist": "PNL"
    },
    {
        "Position": "55",
        "Title": "Confident (feat. Chance The Rapper)",
        "Artist": "Justin Bieber"
    },
    {
        "Position": "56",
        "Title": "Just a Lil Bit",
        "Artist": "50 Cent"
    },
    {
        "Position": "57",
        "Title": "Commas",
        "Artist": "Ayra Starr"
    },
    {
        "Position": "58",
        "Title": "Par amour (feat. Maître Gims)",
        "Artist": "Dadju"
    },
    {
        "Position": "59",
        "Title": "Loin de moi",
        "Artist": "Naza"
    },
    {
        "Position": "60",
        "Title": "Allom Ya Amaa",
        "Artist": "ايمان الشريف"
    },
    {
        "Position": "61",
        "Title": "Twe Twe",
        "Artist": "Kizz Daniel & Davido"
    },
    {
        "Position": "62",
        "Title": "Qalu Li Eian",
        "Artist": "طلال الساتة"
    },
    {
        "Position": "63",
        "Title": "Makila : Wablé",
        "Artist": "Dadju & Tayc"
    },
    {
        "Position": "64",
        "Title": "Egwu",
        "Artist": "Chike & MohBad"
    },
    {
        "Position": "65",
        "Title": "Ensemble",
        "Artist": "Franglish"
    },
    {
        "Position": "66",
        "Title": "Tattoo",
        "Artist": "Loreen"
    },
    {
        "Position": "67",
        "Title": "SL",
        "Artist": "Fally Ipupa"
    },
    {
        "Position": "68",
        "Title": "MH",
        "Artist": "Fally Ipupa"
    },
    {
        "Position": "69",
        "Title": "Wayeh",
        "Artist": "THEODORT"
    },
    {
        "Position": "70",
        "Title": "reason",
        "Artist": "Omah Lay"
    },
    {
        "Position": "71",
        "Title": "Lady D",
        "Artist": "Fally Ipupa"
    },
    {
        "Position": "72",
        "Title": "Commandante",
        "Artist": "Ya Levis"
    },
    {
        "Position": "73",
        "Title": "Halo",
        "Artist": "Beyoncé"
    },
    {
        "Position": "74",
        "Title": "Le monde ou rien",
        "Artist": "PNL"
    },
    {
        "Position": "75",
        "Title": "Harleys in Hawaii",
        "Artist": "Katy Perry"
    },
    {
        "Position": "76",
        "Title": "10 / 10",
        "Artist": "GIMS, Dadju & Alonzo"
    },
    {
        "Position": "77",
        "Title": "Timeless",
        "Artist": "The Weeknd & Playboi Carti"
    },
    {
        "Position": "78",
        "Title": "Reminder",
        "Artist": "The Weeknd"
    },
    {
        "Position": "79",
        "Title": "Miss Me (feat. Lil Wayne)",
        "Artist": "Drake"
    },
    {
        "Position": "80",
        "Title": "Donna Imma",
        "Artist": "Franglish"
    },
    {
        "Position": "81",
        "Title": "Brisé (Pilule Bleue)",
        "Artist": "GIMS"
    },
    {
        "Position": "82",
        "Title": "Ogechi (feat. Davido) [Remix]",
        "Artist": "BoyPee, Hyce & Brown Joel"
    },
    {
        "Position": "83",
        "Title": "MARCH AM",
        "Artist": "Rema"
    },
    {
        "Position": "84",
        "Title": "See You Again (feat. Charlie Puth)",
        "Artist": "Wiz Khalifa"
    },
    {
        "Position": "85",
        "Title": "Piece of My Heart (feat. Brent Faiyaz)",
        "Artist": "Wizkid"
    },
    {
        "Position": "86",
        "Title": "Common Person",
        "Artist": "Burna Boy"
    },
    {
        "Position": "87",
        "Title": "On va t'attraper (feat. Josey)",
        "Artist": "Elow'n"
    },
    {
        "Position": "88",
        "Title": "Comme moi (feat. Tiakola)",
        "Artist": "Ronisia"
    },
    {
        "Position": "89",
        "Title": "One Dance (feat. Wizkid & Kyla)",
        "Artist": "Drake"
    },
    {
        "Position": "90",
        "Title": "HAUSAPIANO (Remix)",
        "Artist": "Kvng Vinci & Zerrydl"
    },
    {
        "Position": "91",
        "Title": "Avec classe",
        "Artist": "Corneille, Aya Nakamura & Trinix"
    },
    {
        "Position": "92",
        "Title": "Dis-moi oui",
        "Artist": "PLK"
    },
    {
        "Position": "93",
        "Title": "سورة المائدة",
        "Artist": "القارئ محمد الفقيه"
    },
    {
        "Position": "94",
        "Title": "Fimbu (feat. Didi B, Ste Milano, Tam Sir & 3xdavs)",
        "Artist": "Team Paiya"
    },
    {
        "Position": "95",
        "Title": "Confuse (feat. Mia Guisse & AMADEUS)",
        "Artist": "Wally B. Seck"
    },
    {
        "Position": "96",
        "Title": "Bakalos",
        "Artist": "Fally Ipupa"
    },
    {
        "Position": "97",
        "Title": "Lamborghini",
        "Artist": "Naza"
    },
    {
        "Position": "98",
        "Title": "Lelo",
        "Artist": "DJ Faya & Fally Ipupa"
    },
    {
        "Position": "99",
        "Title": "De La Renta",
        "Artist": "Fally Ipupa"
    },
    {
        "Position": "100",
        "Title": "Onizuka",
        "Artist": "PNL"
    }
]