[
    {
        "SongID": 51,
        "Position": 37
    },
    {
        "SongID": 109,
        "Position": 78
    },
    {
        "SongID": 182,
        "Position": 47
    },
    {
        "SongID": 274,
        "Position": 99
    },
    {
        "SongID": 277,
        "Position": 91
    },
    {
        "SongID": 293,
        "Position": 54
    },
    {
        "SongID": 309,
        "Position": 68
    },
    {
        "SongID": 357,
        "Position": 71
    },
    {
        "SongID": 469,
        "Position": 46
    },
    {
        "SongID": 508,
        "Position": 62
    },
    {
        "SongID": 603,
        "Position": 82
    },
    {
        "SongID": 1004,
        "Position": 57
    },
    {
        "SongID": 1063,
        "Position": 74
    },
    {
        "SongID": 1980,
        "Position": 98
    },
    {
        "SongID": 2255,
        "Position": 70
    },
    {
        "SongID": 2642,
        "Position": 59
    },
    {
        "SongID": 3071,
        "Position": 92
    },
    {
        "SongID": 3136,
        "Position": 93
    },
    {
        "SongID": 4019,
        "Position": 60
    },
    {
        "SongID": 4021,
        "Position": 76
    },
    {
        "SongID": 4300,
        "Position": 100
    },
    {
        "SongID": 7332,
        "Position": 61
    },
    {
        "SongID": 8571,
        "Position": 63
    },
    {
        "SongID": 9782,
        "Position": 51
    },
    {
        "SongID": 9836,
        "Position": 83
    },
    {
        "SongID": 11366,
        "Position": 95
    },
    {
        "SongID": 12447,
        "Position": 50
    },
    {
        "SongID": 12451,
        "Position": 24
    },
    {
        "SongID": 12995,
        "Position": 44
    },
    {
        "SongID": 13521,
        "Position": 49
    },
    {
        "SongID": 14177,
        "Position": 29
    },
    {
        "SongID": 43875,
        "Position": 30
    },
    {
        "SongID": 63074,
        "Position": 94
    },
    {
        "SongID": 77327,
        "Position": 67
    },
    {
        "SongID": 111110,
        "Position": 41
    },
    {
        "SongID": 113593,
        "Position": 79
    },
    {
        "SongID": 114660,
        "Position": 55
    },
    {
        "SongID": 118679,
        "Position": 80
    },
    {
        "SongID": 126335,
        "Position": 90
    },
    {
        "SongID": 130794,
        "Position": 75
    },
    {
        "SongID": 179311,
        "Position": 69
    },
    {
        "SongID": 198095,
        "Position": 65
    },
    {
        "SongID": 501280,
        "Position": 17
    },
    {
        "SongID": 501286,
        "Position": 16
    },
    {
        "SongID": 501515,
        "Position": 66
    },
    {
        "SongID": 540082,
        "Position": 56
    },
    {
        "SongID": 561604,
        "Position": 81
    },
    {
        "SongID": 600127,
        "Position": 19
    },
    {
        "SongID": 600502,
        "Position": 89
    },
    {
        "SongID": 600826,
        "Position": 96
    },
    {
        "SongID": 601484,
        "Position": 14
    },
    {
        "SongID": 601491,
        "Position": 20
    },
    {
        "SongID": 601525,
        "Position": 21
    },
    {
        "SongID": 601638,
        "Position": 73
    },
    {
        "SongID": 605371,
        "Position": 40
    },
    {
        "SongID": 605571,
        "Position": 12
    },
    {
        "SongID": 606062,
        "Position": 48
    },
    {
        "SongID": 606314,
        "Position": 72
    },
    {
        "SongID": 611589,
        "Position": 85
    },
    {
        "SongID": 612129,
        "Position": 38
    },
    {
        "SongID": 612548,
        "Position": 43
    },
    {
        "SongID": 612633,
        "Position": 77
    },
    {
        "SongID": 613757,
        "Position": 42
    },
    {
        "SongID": 613964,
        "Position": 64
    },
    {
        "SongID": 619567,
        "Position": 25
    },
    {
        "SongID": 620354,
        "Position": 7
    },
    {
        "SongID": 622795,
        "Position": 45
    },
    {
        "SongID": 723309,
        "Position": 13
    },
    {
        "SongID": 723484,
        "Position": 4
    },
    {
        "SongID": 724337,
        "Position": 39
    },
    {
        "SongID": 724375,
        "Position": 33
    },
    {
        "SongID": 728959,
        "Position": 31
    },
    {
        "SongID": 753666,
        "Position": 36
    },
    {
        "SongID": 923685,
        "Position": 58
    },
    {
        "SongID": 947369,
        "Position": 1
    },
    {
        "SongID": 947370,
        "Position": 8
    },
    {
        "SongID": 947371,
        "Position": 10
    },
    {
        "SongID": 947372,
        "Position": 5
    },
    {
        "SongID": 947373,
        "Position": 11
    },
    {
        "SongID": 947374,
        "Position": 9
    },
    {
        "SongID": 947375,
        "Position": 2
    },
    {
        "SongID": 947376,
        "Position": 18
    },
    {
        "SongID": 947377,
        "Position": 22
    },
    {
        "SongID": 947378,
        "Position": 27
    },
    {
        "SongID": 947379,
        "Position": 28
    },
    {
        "SongID": 947380,
        "Position": 6
    },
    {
        "SongID": 947381,
        "Position": 23
    },
    {
        "SongID": 947382,
        "Position": 52
    },
    {
        "SongID": 947383,
        "Position": 26
    },
    {
        "SongID": 972654,
        "Position": 3
    },
    {
        "SongID": 975097,
        "Position": 97
    },
    {
        "SongID": 975098,
        "Position": 53
    },
    {
        "SongID": 975301,
        "Position": 15
    },
    {
        "SongID": 975302,
        "Position": 34
    },
    {
        "SongID": 975303,
        "Position": 35
    },
    {
        "SongID": 975304,
        "Position": 84
    },
    {
        "SongID": 975305,
        "Position": 86
    },
    {
        "SongID": 975306,
        "Position": 87
    },
    {
        "SongID": 975307,
        "Position": 88
    },
    {
        "SongID": 976721,
        "Position": 32
    }
]