[
    {
        "SongID": 66,
        "Position": 59
    },
    {
        "SongID": 113,
        "Position": 18
    },
    {
        "SongID": 1565,
        "Position": 79
    },
    {
        "SongID": 4456,
        "Position": 12
    },
    {
        "SongID": 5430,
        "Position": 72
    },
    {
        "SongID": 6082,
        "Position": 22
    },
    {
        "SongID": 6172,
        "Position": 4
    },
    {
        "SongID": 7890,
        "Position": 32
    },
    {
        "SongID": 9713,
        "Position": 93
    },
    {
        "SongID": 10889,
        "Position": 55
    },
    {
        "SongID": 10890,
        "Position": 86
    },
    {
        "SongID": 11835,
        "Position": 98
    },
    {
        "SongID": 11984,
        "Position": 76
    },
    {
        "SongID": 11985,
        "Position": 84
    },
    {
        "SongID": 12447,
        "Position": 58
    },
    {
        "SongID": 12451,
        "Position": 42
    },
    {
        "SongID": 12453,
        "Position": 82
    },
    {
        "SongID": 13158,
        "Position": 53
    },
    {
        "SongID": 13521,
        "Position": 49
    },
    {
        "SongID": 13707,
        "Position": 26
    },
    {
        "SongID": 14874,
        "Position": 100
    },
    {
        "SongID": 16219,
        "Position": 37
    },
    {
        "SongID": 16944,
        "Position": 24
    },
    {
        "SongID": 17548,
        "Position": 80
    },
    {
        "SongID": 20422,
        "Position": 65
    },
    {
        "SongID": 21252,
        "Position": 94
    },
    {
        "SongID": 21975,
        "Position": 39
    },
    {
        "SongID": 21976,
        "Position": 41
    },
    {
        "SongID": 29906,
        "Position": 89
    },
    {
        "SongID": 29909,
        "Position": 88
    },
    {
        "SongID": 30112,
        "Position": 8
    },
    {
        "SongID": 30129,
        "Position": 54
    },
    {
        "SongID": 30682,
        "Position": 70
    },
    {
        "SongID": 31376,
        "Position": 71
    },
    {
        "SongID": 31557,
        "Position": 38
    },
    {
        "SongID": 113374,
        "Position": 27
    },
    {
        "SongID": 118613,
        "Position": 19
    },
    {
        "SongID": 118690,
        "Position": 92
    },
    {
        "SongID": 139919,
        "Position": 69
    },
    {
        "SongID": 139956,
        "Position": 43
    },
    {
        "SongID": 140802,
        "Position": 85
    },
    {
        "SongID": 213762,
        "Position": 56
    },
    {
        "SongID": 213774,
        "Position": 81
    },
    {
        "SongID": 213818,
        "Position": 87
    },
    {
        "SongID": 501280,
        "Position": 17
    },
    {
        "SongID": 501288,
        "Position": 7
    },
    {
        "SongID": 501328,
        "Position": 16
    },
    {
        "SongID": 501456,
        "Position": 78
    },
    {
        "SongID": 501829,
        "Position": 11
    },
    {
        "SongID": 501830,
        "Position": 28
    },
    {
        "SongID": 501831,
        "Position": 5
    },
    {
        "SongID": 501833,
        "Position": 66
    },
    {
        "SongID": 501835,
        "Position": 44
    },
    {
        "SongID": 501837,
        "Position": 63
    },
    {
        "SongID": 501840,
        "Position": 6
    },
    {
        "SongID": 501841,
        "Position": 46
    },
    {
        "SongID": 501842,
        "Position": 60
    },
    {
        "SongID": 501857,
        "Position": 62
    },
    {
        "SongID": 501859,
        "Position": 33
    },
    {
        "SongID": 501861,
        "Position": 77
    },
    {
        "SongID": 501869,
        "Position": 57
    },
    {
        "SongID": 530580,
        "Position": 2
    },
    {
        "SongID": 531739,
        "Position": 25
    },
    {
        "SongID": 533956,
        "Position": 99
    },
    {
        "SongID": 533968,
        "Position": 21
    },
    {
        "SongID": 538737,
        "Position": 90
    },
    {
        "SongID": 538771,
        "Position": 50
    },
    {
        "SongID": 538811,
        "Position": 34
    },
    {
        "SongID": 538856,
        "Position": 48
    },
    {
        "SongID": 539009,
        "Position": 83
    },
    {
        "SongID": 572889,
        "Position": 13
    },
    {
        "SongID": 600127,
        "Position": 36
    },
    {
        "SongID": 600128,
        "Position": 35
    },
    {
        "SongID": 600247,
        "Position": 10
    },
    {
        "SongID": 600248,
        "Position": 74
    },
    {
        "SongID": 600249,
        "Position": 23
    },
    {
        "SongID": 600472,
        "Position": 51
    },
    {
        "SongID": 600584,
        "Position": 96
    },
    {
        "SongID": 600587,
        "Position": 20
    },
    {
        "SongID": 600646,
        "Position": 97
    },
    {
        "SongID": 600877,
        "Position": 29
    },
    {
        "SongID": 600878,
        "Position": 9
    },
    {
        "SongID": 600879,
        "Position": 15
    },
    {
        "SongID": 600880,
        "Position": 31
    },
    {
        "SongID": 600881,
        "Position": 91
    },
    {
        "SongID": 600885,
        "Position": 75
    },
    {
        "SongID": 601181,
        "Position": 30
    },
    {
        "SongID": 601495,
        "Position": 40
    },
    {
        "SongID": 601496,
        "Position": 67
    },
    {
        "SongID": 601497,
        "Position": 64
    },
    {
        "SongID": 601499,
        "Position": 52
    },
    {
        "SongID": 601596,
        "Position": 1
    },
    {
        "SongID": 601598,
        "Position": 14
    },
    {
        "SongID": 606324,
        "Position": 3
    },
    {
        "SongID": 606325,
        "Position": 45
    },
    {
        "SongID": 606326,
        "Position": 47
    },
    {
        "SongID": 606327,
        "Position": 61
    },
    {
        "SongID": 606328,
        "Position": 68
    },
    {
        "SongID": 606329,
        "Position": 73
    },
    {
        "SongID": 606330,
        "Position": 95
    }
]