[
    {
        "SongID": 27,
        "Position": 53
    },
    {
        "SongID": 192,
        "Position": 86
    },
    {
        "SongID": 218,
        "Position": 75
    },
    {
        "SongID": 277,
        "Position": 72
    },
    {
        "SongID": 326,
        "Position": 74
    },
    {
        "SongID": 390,
        "Position": 82
    },
    {
        "SongID": 731,
        "Position": 1
    },
    {
        "SongID": 777,
        "Position": 64
    },
    {
        "SongID": 1063,
        "Position": 61
    },
    {
        "SongID": 1146,
        "Position": 73
    },
    {
        "SongID": 2924,
        "Position": 11
    },
    {
        "SongID": 8842,
        "Position": 40
    },
    {
        "SongID": 10688,
        "Position": 87
    },
    {
        "SongID": 12447,
        "Position": 19
    },
    {
        "SongID": 12449,
        "Position": 43
    },
    {
        "SongID": 12451,
        "Position": 14
    },
    {
        "SongID": 12453,
        "Position": 41
    },
    {
        "SongID": 12499,
        "Position": 54
    },
    {
        "SongID": 12597,
        "Position": 88
    },
    {
        "SongID": 12959,
        "Position": 29
    },
    {
        "SongID": 13093,
        "Position": 79
    },
    {
        "SongID": 13136,
        "Position": 25
    },
    {
        "SongID": 13521,
        "Position": 42
    },
    {
        "SongID": 13629,
        "Position": 90
    },
    {
        "SongID": 13631,
        "Position": 89
    },
    {
        "SongID": 14868,
        "Position": 78
    },
    {
        "SongID": 15855,
        "Position": 52
    },
    {
        "SongID": 18496,
        "Position": 10
    },
    {
        "SongID": 31577,
        "Position": 35
    },
    {
        "SongID": 87799,
        "Position": 60
    },
    {
        "SongID": 113593,
        "Position": 76
    },
    {
        "SongID": 118613,
        "Position": 9
    },
    {
        "SongID": 118993,
        "Position": 51
    },
    {
        "SongID": 146698,
        "Position": 24
    },
    {
        "SongID": 149427,
        "Position": 39
    },
    {
        "SongID": 201753,
        "Position": 33
    },
    {
        "SongID": 309424,
        "Position": 46
    },
    {
        "SongID": 501280,
        "Position": 5
    },
    {
        "SongID": 501282,
        "Position": 55
    },
    {
        "SongID": 501286,
        "Position": 36
    },
    {
        "SongID": 501288,
        "Position": 69
    },
    {
        "SongID": 501301,
        "Position": 68
    },
    {
        "SongID": 501328,
        "Position": 26
    },
    {
        "SongID": 501561,
        "Position": 20
    },
    {
        "SongID": 501612,
        "Position": 92
    },
    {
        "SongID": 502086,
        "Position": 58
    },
    {
        "SongID": 503594,
        "Position": 80
    },
    {
        "SongID": 504620,
        "Position": 95
    },
    {
        "SongID": 530005,
        "Position": 84
    },
    {
        "SongID": 534071,
        "Position": 48
    },
    {
        "SongID": 538742,
        "Position": 98
    },
    {
        "SongID": 538942,
        "Position": 37
    },
    {
        "SongID": 539122,
        "Position": 30
    },
    {
        "SongID": 539579,
        "Position": 47
    },
    {
        "SongID": 539581,
        "Position": 57
    },
    {
        "SongID": 539806,
        "Position": 28
    },
    {
        "SongID": 540082,
        "Position": 66
    },
    {
        "SongID": 540771,
        "Position": 27
    },
    {
        "SongID": 541761,
        "Position": 34
    },
    {
        "SongID": 544627,
        "Position": 67
    },
    {
        "SongID": 545257,
        "Position": 91
    },
    {
        "SongID": 547036,
        "Position": 2
    },
    {
        "SongID": 547765,
        "Position": 22
    },
    {
        "SongID": 548494,
        "Position": 85
    },
    {
        "SongID": 572794,
        "Position": 96
    },
    {
        "SongID": 600127,
        "Position": 13
    },
    {
        "SongID": 600128,
        "Position": 17
    },
    {
        "SongID": 601012,
        "Position": 99
    },
    {
        "SongID": 601013,
        "Position": 70
    },
    {
        "SongID": 601638,
        "Position": 15
    },
    {
        "SongID": 601980,
        "Position": 93
    },
    {
        "SongID": 604871,
        "Position": 81
    },
    {
        "SongID": 605403,
        "Position": 83
    },
    {
        "SongID": 605440,
        "Position": 32
    },
    {
        "SongID": 605453,
        "Position": 23
    },
    {
        "SongID": 605471,
        "Position": 94
    },
    {
        "SongID": 606050,
        "Position": 4
    },
    {
        "SongID": 606825,
        "Position": 6
    },
    {
        "SongID": 606917,
        "Position": 44
    },
    {
        "SongID": 609026,
        "Position": 97
    },
    {
        "SongID": 612235,
        "Position": 18
    },
    {
        "SongID": 618130,
        "Position": 71
    },
    {
        "SongID": 722583,
        "Position": 38
    },
    {
        "SongID": 723623,
        "Position": 50
    },
    {
        "SongID": 724785,
        "Position": 59
    },
    {
        "SongID": 728857,
        "Position": 3
    },
    {
        "SongID": 729423,
        "Position": 49
    },
    {
        "SongID": 730224,
        "Position": 31
    },
    {
        "SongID": 753771,
        "Position": 77
    },
    {
        "SongID": 753786,
        "Position": 63
    },
    {
        "SongID": 778026,
        "Position": 100
    },
    {
        "SongID": 778289,
        "Position": 16
    },
    {
        "SongID": 778294,
        "Position": 7
    },
    {
        "SongID": 778296,
        "Position": 12
    },
    {
        "SongID": 778297,
        "Position": 8
    },
    {
        "SongID": 924117,
        "Position": 21
    },
    {
        "SongID": 924118,
        "Position": 45
    },
    {
        "SongID": 924119,
        "Position": 56
    },
    {
        "SongID": 924120,
        "Position": 62
    },
    {
        "SongID": 924121,
        "Position": 65
    }
]