[
    {
        "SongID": 800000,
        "Position": 1
    },
    {
        "SongID": 800001,
        "Position": 2
    },
    {
        "SongID": 800002,
        "Position": 3
    },
    {
        "SongID": 800003,
        "Position": 4
    },
    {
        "SongID": 800004,
        "Position": 5
    },
    {
        "SongID": 800005,
        "Position": 6
    },
    {
        "SongID": 800006,
        "Position": 7
    },
    {
        "SongID": 800007,
        "Position": 8
    },
    {
        "SongID": 800008,
        "Position": 9
    },
    {
        "SongID": 800009,
        "Position": 10
    },
    {
        "SongID": 800010,
        "Position": 11
    },
    {
        "SongID": 800011,
        "Position": 12
    },
    {
        "SongID": 800012,
        "Position": 13
    },
    {
        "SongID": 800013,
        "Position": 14
    },
    {
        "SongID": 800014,
        "Position": 15
    },
    {
        "SongID": 800015,
        "Position": 16
    },
    {
        "SongID": 800016,
        "Position": 17
    },
    {
        "SongID": 800017,
        "Position": 18
    },
    {
        "SongID": 800018,
        "Position": 19
    },
    {
        "SongID": 800019,
        "Position": 20
    },
    {
        "SongID": 800020,
        "Position": 21
    },
    {
        "SongID": 800021,
        "Position": 22
    },
    {
        "SongID": 800022,
        "Position": 23
    },
    {
        "SongID": 800023,
        "Position": 24
    },
    {
        "SongID": 800024,
        "Position": 25
    },
    {
        "SongID": 800025,
        "Position": 26
    },
    {
        "SongID": 800026,
        "Position": 27
    },
    {
        "SongID": 800027,
        "Position": 28
    },
    {
        "SongID": 800028,
        "Position": 29
    },
    {
        "SongID": 800029,
        "Position": 30
    },
    {
        "SongID": 800030,
        "Position": 31
    },
    {
        "SongID": 800031,
        "Position": 32
    },
    {
        "SongID": 800032,
        "Position": 33
    },
    {
        "SongID": 800033,
        "Position": 34
    },
    {
        "SongID": 800034,
        "Position": 35
    },
    {
        "SongID": 800035,
        "Position": 36
    },
    {
        "SongID": 800036,
        "Position": 37
    },
    {
        "SongID": 800037,
        "Position": 38
    },
    {
        "SongID": 800038,
        "Position": 39
    },
    {
        "SongID": 800039,
        "Position": 40
    },
    {
        "SongID": 800040,
        "Position": 41
    },
    {
        "SongID": 800041,
        "Position": 42
    },
    {
        "SongID": 800042,
        "Position": 43
    },
    {
        "SongID": 800043,
        "Position": 44
    },
    {
        "SongID": 800044,
        "Position": 45
    },
    {
        "SongID": 800045,
        "Position": 46
    },
    {
        "SongID": 800046,
        "Position": 47
    },
    {
        "SongID": 800047,
        "Position": 48
    },
    {
        "SongID": 800048,
        "Position": 49
    },
    {
        "SongID": 800049,
        "Position": 50
    },
    {
        "SongID": 800050,
        "Position": 51
    },
    {
        "SongID": 800051,
        "Position": 52
    },
    {
        "SongID": 800052,
        "Position": 53
    },
    {
        "SongID": 800053,
        "Position": 54
    },
    {
        "SongID": 800054,
        "Position": 55
    },
    {
        "SongID": 800055,
        "Position": 56
    },
    {
        "SongID": 800056,
        "Position": 57
    },
    {
        "SongID": 800057,
        "Position": 58
    },
    {
        "SongID": 800058,
        "Position": 59
    },
    {
        "SongID": 800059,
        "Position": 60
    },
    {
        "SongID": 800060,
        "Position": 61
    },
    {
        "SongID": 800061,
        "Position": 62
    },
    {
        "SongID": 800062,
        "Position": 63
    },
    {
        "SongID": 800063,
        "Position": 64
    },
    {
        "SongID": 800064,
        "Position": 65
    },
    {
        "SongID": 800065,
        "Position": 66
    },
    {
        "SongID": 800066,
        "Position": 67
    },
    {
        "SongID": 800067,
        "Position": 68
    },
    {
        "SongID": 800068,
        "Position": 69
    },
    {
        "SongID": 800069,
        "Position": 70
    },
    {
        "SongID": 800070,
        "Position": 71
    },
    {
        "SongID": 800071,
        "Position": 72
    },
    {
        "SongID": 800072,
        "Position": 73
    },
    {
        "SongID": 800073,
        "Position": 74
    },
    {
        "SongID": 800074,
        "Position": 75
    },
    {
        "SongID": 800075,
        "Position": 76
    },
    {
        "SongID": 800076,
        "Position": 77
    },
    {
        "SongID": 800077,
        "Position": 78
    },
    {
        "SongID": 800078,
        "Position": 79
    },
    {
        "SongID": 800079,
        "Position": 80
    },
    {
        "SongID": 800080,
        "Position": 81
    },
    {
        "SongID": 800081,
        "Position": 82
    },
    {
        "SongID": 800082,
        "Position": 83
    },
    {
        "SongID": 800083,
        "Position": 84
    },
    {
        "SongID": 800084,
        "Position": 85
    },
    {
        "SongID": 800085,
        "Position": 86
    },
    {
        "SongID": 800086,
        "Position": 87
    },
    {
        "SongID": 800087,
        "Position": 88
    },
    {
        "SongID": 800088,
        "Position": 89
    },
    {
        "SongID": 800089,
        "Position": 90
    },
    {
        "SongID": 800090,
        "Position": 91
    },
    {
        "SongID": 800091,
        "Position": 92
    },
    {
        "SongID": 800092,
        "Position": 93
    },
    {
        "SongID": 800093,
        "Position": 94
    },
    {
        "SongID": 800094,
        "Position": 95
    },
    {
        "SongID": 800095,
        "Position": 96
    },
    {
        "SongID": 800096,
        "Position": 97
    },
    {
        "SongID": 800097,
        "Position": 98
    },
    {
        "SongID": 800098,
        "Position": 99
    },
    {
        "SongID": 800099,
        "Position": 100
    }
]