[
    {
        "SongID": 113,
        "Position": 62
    },
    {
        "SongID": 416,
        "Position": 75
    },
    {
        "SongID": 562,
        "Position": 9
    },
    {
        "SongID": 2404,
        "Position": 48
    },
    {
        "SongID": 3976,
        "Position": 49
    },
    {
        "SongID": 5619,
        "Position": 65
    },
    {
        "SongID": 6082,
        "Position": 59
    },
    {
        "SongID": 6242,
        "Position": 70
    },
    {
        "SongID": 7646,
        "Position": 30
    },
    {
        "SongID": 8287,
        "Position": 86
    },
    {
        "SongID": 12451,
        "Position": 53
    },
    {
        "SongID": 16126,
        "Position": 18
    },
    {
        "SongID": 18863,
        "Position": 7
    },
    {
        "SongID": 41851,
        "Position": 63
    },
    {
        "SongID": 118719,
        "Position": 87
    },
    {
        "SongID": 119729,
        "Position": 89
    },
    {
        "SongID": 119747,
        "Position": 55
    },
    {
        "SongID": 123797,
        "Position": 99
    },
    {
        "SongID": 126245,
        "Position": 68
    },
    {
        "SongID": 126447,
        "Position": 91
    },
    {
        "SongID": 126475,
        "Position": 41
    },
    {
        "SongID": 126541,
        "Position": 78
    },
    {
        "SongID": 126773,
        "Position": 80
    },
    {
        "SongID": 126803,
        "Position": 8
    },
    {
        "SongID": 138538,
        "Position": 39
    },
    {
        "SongID": 138541,
        "Position": 74
    },
    {
        "SongID": 138544,
        "Position": 50
    },
    {
        "SongID": 138551,
        "Position": 34
    },
    {
        "SongID": 138581,
        "Position": 71
    },
    {
        "SongID": 153660,
        "Position": 61
    },
    {
        "SongID": 153661,
        "Position": 42
    },
    {
        "SongID": 153686,
        "Position": 84
    },
    {
        "SongID": 208380,
        "Position": 97
    },
    {
        "SongID": 211808,
        "Position": 45
    },
    {
        "SongID": 223125,
        "Position": 24
    },
    {
        "SongID": 223232,
        "Position": 85
    },
    {
        "SongID": 501280,
        "Position": 10
    },
    {
        "SongID": 501286,
        "Position": 3
    },
    {
        "SongID": 501299,
        "Position": 12
    },
    {
        "SongID": 501305,
        "Position": 29
    },
    {
        "SongID": 501323,
        "Position": 51
    },
    {
        "SongID": 501441,
        "Position": 19
    },
    {
        "SongID": 501503,
        "Position": 22
    },
    {
        "SongID": 501504,
        "Position": 54
    },
    {
        "SongID": 501511,
        "Position": 44
    },
    {
        "SongID": 501513,
        "Position": 46
    },
    {
        "SongID": 501536,
        "Position": 17
    },
    {
        "SongID": 502390,
        "Position": 69
    },
    {
        "SongID": 502410,
        "Position": 5
    },
    {
        "SongID": 532606,
        "Position": 60
    },
    {
        "SongID": 533132,
        "Position": 92
    },
    {
        "SongID": 538723,
        "Position": 28
    },
    {
        "SongID": 538941,
        "Position": 88
    },
    {
        "SongID": 538990,
        "Position": 77
    },
    {
        "SongID": 539836,
        "Position": 73
    },
    {
        "SongID": 541901,
        "Position": 15
    },
    {
        "SongID": 556824,
        "Position": 37
    },
    {
        "SongID": 600127,
        "Position": 6
    },
    {
        "SongID": 601166,
        "Position": 23
    },
    {
        "SongID": 601491,
        "Position": 21
    },
    {
        "SongID": 601525,
        "Position": 4
    },
    {
        "SongID": 601527,
        "Position": 64
    },
    {
        "SongID": 601570,
        "Position": 16
    },
    {
        "SongID": 601862,
        "Position": 81
    },
    {
        "SongID": 601872,
        "Position": 57
    },
    {
        "SongID": 601978,
        "Position": 1
    },
    {
        "SongID": 602196,
        "Position": 35
    },
    {
        "SongID": 602221,
        "Position": 82
    },
    {
        "SongID": 602224,
        "Position": 32
    },
    {
        "SongID": 602226,
        "Position": 38
    },
    {
        "SongID": 602229,
        "Position": 40
    },
    {
        "SongID": 605448,
        "Position": 13
    },
    {
        "SongID": 605452,
        "Position": 31
    },
    {
        "SongID": 605505,
        "Position": 2
    },
    {
        "SongID": 605506,
        "Position": 58
    },
    {
        "SongID": 607875,
        "Position": 98
    },
    {
        "SongID": 610370,
        "Position": 36
    },
    {
        "SongID": 610977,
        "Position": 76
    },
    {
        "SongID": 611589,
        "Position": 11
    },
    {
        "SongID": 611792,
        "Position": 94
    },
    {
        "SongID": 611999,
        "Position": 47
    },
    {
        "SongID": 612011,
        "Position": 95
    },
    {
        "SongID": 612021,
        "Position": 33
    },
    {
        "SongID": 612022,
        "Position": 79
    },
    {
        "SongID": 612548,
        "Position": 83
    },
    {
        "SongID": 618780,
        "Position": 26
    },
    {
        "SongID": 618781,
        "Position": 20
    },
    {
        "SongID": 618782,
        "Position": 72
    },
    {
        "SongID": 618905,
        "Position": 90
    },
    {
        "SongID": 618921,
        "Position": 56
    },
    {
        "SongID": 619012,
        "Position": 96
    },
    {
        "SongID": 619567,
        "Position": 27
    },
    {
        "SongID": 624271,
        "Position": 14
    },
    {
        "SongID": 723095,
        "Position": 25
    },
    {
        "SongID": 723100,
        "Position": 66
    },
    {
        "SongID": 723101,
        "Position": 52
    },
    {
        "SongID": 723184,
        "Position": 93
    },
    {
        "SongID": 723220,
        "Position": 43
    },
    {
        "SongID": 723686,
        "Position": 67
    },
    {
        "SongID": 723687,
        "Position": 100
    }
]