[
    {
        "SongID": 9,
        "Position": 15
    },
    {
        "SongID": 15,
        "Position": 48
    },
    {
        "SongID": 19,
        "Position": 130
    },
    {
        "SongID": 27,
        "Position": 187
    },
    {
        "SongID": 79,
        "Position": 80
    },
    {
        "SongID": 110,
        "Position": 111
    },
    {
        "SongID": 121,
        "Position": 122
    },
    {
        "SongID": 141,
        "Position": 142
    },
    {
        "SongID": 249,
        "Position": 62
    },
    {
        "SongID": 358,
        "Position": 75
    },
    {
        "SongID": 359,
        "Position": 164
    },
    {
        "SongID": 450,
        "Position": 154
    },
    {
        "SongID": 481,
        "Position": 46
    },
    {
        "SongID": 556,
        "Position": 189
    },
    {
        "SongID": 603,
        "Position": 136
    },
    {
        "SongID": 638,
        "Position": 18
    },
    {
        "SongID": 640,
        "Position": 145
    },
    {
        "SongID": 834,
        "Position": 83
    },
    {
        "SongID": 836,
        "Position": 118
    },
    {
        "SongID": 1004,
        "Position": 94
    },
    {
        "SongID": 1031,
        "Position": 165
    },
    {
        "SongID": 1072,
        "Position": 61
    },
    {
        "SongID": 1100,
        "Position": 152
    },
    {
        "SongID": 1255,
        "Position": 126
    },
    {
        "SongID": 1344,
        "Position": 74
    },
    {
        "SongID": 1421,
        "Position": 41
    },
    {
        "SongID": 1517,
        "Position": 183
    },
    {
        "SongID": 1707,
        "Position": 123
    },
    {
        "SongID": 1727,
        "Position": 150
    },
    {
        "SongID": 1747,
        "Position": 88
    },
    {
        "SongID": 1823,
        "Position": 175
    },
    {
        "SongID": 2171,
        "Position": 69
    },
    {
        "SongID": 2273,
        "Position": 127
    },
    {
        "SongID": 2326,
        "Position": 77
    },
    {
        "SongID": 2368,
        "Position": 174
    },
    {
        "SongID": 2389,
        "Position": 151
    },
    {
        "SongID": 2608,
        "Position": 121
    },
    {
        "SongID": 2769,
        "Position": 63
    },
    {
        "SongID": 2850,
        "Position": 98
    },
    {
        "SongID": 2896,
        "Position": 91
    },
    {
        "SongID": 3137,
        "Position": 99
    },
    {
        "SongID": 3781,
        "Position": 199
    },
    {
        "SongID": 3782,
        "Position": 84
    },
    {
        "SongID": 3783,
        "Position": 185
    },
    {
        "SongID": 4329,
        "Position": 182
    },
    {
        "SongID": 4616,
        "Position": 195
    },
    {
        "SongID": 4668,
        "Position": 181
    },
    {
        "SongID": 4676,
        "Position": 55
    },
    {
        "SongID": 4923,
        "Position": 160
    },
    {
        "SongID": 5044,
        "Position": 92
    },
    {
        "SongID": 5492,
        "Position": 114
    },
    {
        "SongID": 8139,
        "Position": 87
    },
    {
        "SongID": 8254,
        "Position": 166
    },
    {
        "SongID": 8571,
        "Position": 128
    },
    {
        "SongID": 8679,
        "Position": 116
    },
    {
        "SongID": 9836,
        "Position": 51
    },
    {
        "SongID": 10100,
        "Position": 97
    },
    {
        "SongID": 10572,
        "Position": 117
    },
    {
        "SongID": 10574,
        "Position": 54
    },
    {
        "SongID": 11281,
        "Position": 167
    },
    {
        "SongID": 12447,
        "Position": 191
    },
    {
        "SongID": 12450,
        "Position": 31
    },
    {
        "SongID": 12451,
        "Position": 50
    },
    {
        "SongID": 12959,
        "Position": 82
    },
    {
        "SongID": 12995,
        "Position": 68
    },
    {
        "SongID": 14882,
        "Position": 120
    },
    {
        "SongID": 15070,
        "Position": 78
    },
    {
        "SongID": 16256,
        "Position": 170
    },
    {
        "SongID": 19036,
        "Position": 141
    },
    {
        "SongID": 19074,
        "Position": 34
    },
    {
        "SongID": 19678,
        "Position": 168
    },
    {
        "SongID": 19687,
        "Position": 104
    },
    {
        "SongID": 20191,
        "Position": 109
    },
    {
        "SongID": 23762,
        "Position": 40
    },
    {
        "SongID": 24964,
        "Position": 153
    },
    {
        "SongID": 24969,
        "Position": 105
    },
    {
        "SongID": 27221,
        "Position": 161
    },
    {
        "SongID": 28765,
        "Position": 57
    },
    {
        "SongID": 29061,
        "Position": 112
    },
    {
        "SongID": 118719,
        "Position": 188
    },
    {
        "SongID": 118776,
        "Position": 148
    },
    {
        "SongID": 120348,
        "Position": 132
    },
    {
        "SongID": 120381,
        "Position": 173
    },
    {
        "SongID": 121370,
        "Position": 103
    },
    {
        "SongID": 121371,
        "Position": 107
    },
    {
        "SongID": 121442,
        "Position": 144
    },
    {
        "SongID": 122636,
        "Position": 184
    },
    {
        "SongID": 122646,
        "Position": 129
    },
    {
        "SongID": 122984,
        "Position": 194
    },
    {
        "SongID": 123006,
        "Position": 133
    },
    {
        "SongID": 123014,
        "Position": 102
    },
    {
        "SongID": 124222,
        "Position": 196
    },
    {
        "SongID": 124435,
        "Position": 180
    },
    {
        "SongID": 124437,
        "Position": 134
    },
    {
        "SongID": 125428,
        "Position": 179
    },
    {
        "SongID": 125434,
        "Position": 155
    },
    {
        "SongID": 125458,
        "Position": 56
    },
    {
        "SongID": 125744,
        "Position": 177
    },
    {
        "SongID": 126641,
        "Position": 178
    },
    {
        "SongID": 126827,
        "Position": 143
    },
    {
        "SongID": 136686,
        "Position": 73
    },
    {
        "SongID": 198110,
        "Position": 200
    },
    {
        "SongID": 198112,
        "Position": 138
    },
    {
        "SongID": 198120,
        "Position": 89
    },
    {
        "SongID": 212319,
        "Position": 115
    },
    {
        "SongID": 212322,
        "Position": 101
    },
    {
        "SongID": 501280,
        "Position": 22
    },
    {
        "SongID": 501286,
        "Position": 19
    },
    {
        "SongID": 501304,
        "Position": 193
    },
    {
        "SongID": 501305,
        "Position": 42
    },
    {
        "SongID": 501371,
        "Position": 139
    },
    {
        "SongID": 501375,
        "Position": 70
    },
    {
        "SongID": 501441,
        "Position": 27
    },
    {
        "SongID": 501508,
        "Position": 106
    },
    {
        "SongID": 501515,
        "Position": 35
    },
    {
        "SongID": 501530,
        "Position": 137
    },
    {
        "SongID": 501649,
        "Position": 58
    },
    {
        "SongID": 501650,
        "Position": 29
    },
    {
        "SongID": 502819,
        "Position": 163
    },
    {
        "SongID": 530419,
        "Position": 53
    },
    {
        "SongID": 531609,
        "Position": 95
    },
    {
        "SongID": 533594,
        "Position": 79
    },
    {
        "SongID": 533595,
        "Position": 171
    },
    {
        "SongID": 533596,
        "Position": 119
    },
    {
        "SongID": 538675,
        "Position": 66
    },
    {
        "SongID": 538723,
        "Position": 108
    },
    {
        "SongID": 538727,
        "Position": 36
    },
    {
        "SongID": 538961,
        "Position": 192
    },
    {
        "SongID": 539145,
        "Position": 147
    },
    {
        "SongID": 539830,
        "Position": 176
    },
    {
        "SongID": 539837,
        "Position": 146
    },
    {
        "SongID": 539965,
        "Position": 135
    },
    {
        "SongID": 540082,
        "Position": 140
    },
    {
        "SongID": 545950,
        "Position": 110
    },
    {
        "SongID": 545963,
        "Position": 86
    },
    {
        "SongID": 546004,
        "Position": 59
    },
    {
        "SongID": 552418,
        "Position": 71
    },
    {
        "SongID": 572872,
        "Position": 45
    },
    {
        "SongID": 600127,
        "Position": 26
    },
    {
        "SongID": 600130,
        "Position": 38
    },
    {
        "SongID": 600131,
        "Position": 90
    },
    {
        "SongID": 600861,
        "Position": 23
    },
    {
        "SongID": 601130,
        "Position": 16
    },
    {
        "SongID": 601166,
        "Position": 72
    },
    {
        "SongID": 601171,
        "Position": 3
    },
    {
        "SongID": 601484,
        "Position": 156
    },
    {
        "SongID": 601491,
        "Position": 11
    },
    {
        "SongID": 601525,
        "Position": 9
    },
    {
        "SongID": 601527,
        "Position": 64
    },
    {
        "SongID": 601570,
        "Position": 28
    },
    {
        "SongID": 601586,
        "Position": 21
    },
    {
        "SongID": 605176,
        "Position": 124
    },
    {
        "SongID": 605184,
        "Position": 158
    },
    {
        "SongID": 605452,
        "Position": 159
    },
    {
        "SongID": 605485,
        "Position": 100
    },
    {
        "SongID": 610370,
        "Position": 49
    },
    {
        "SongID": 610977,
        "Position": 186
    },
    {
        "SongID": 611266,
        "Position": 169
    },
    {
        "SongID": 611339,
        "Position": 157
    },
    {
        "SongID": 611340,
        "Position": 131
    },
    {
        "SongID": 611589,
        "Position": 30
    },
    {
        "SongID": 611898,
        "Position": 43
    },
    {
        "SongID": 612672,
        "Position": 149
    },
    {
        "SongID": 618952,
        "Position": 76
    },
    {
        "SongID": 619567,
        "Position": 25
    },
    {
        "SongID": 619679,
        "Position": 96
    },
    {
        "SongID": 624204,
        "Position": 172
    },
    {
        "SongID": 722599,
        "Position": 162
    },
    {
        "SongID": 722600,
        "Position": 10
    },
    {
        "SongID": 723287,
        "Position": 17
    },
    {
        "SongID": 723309,
        "Position": 5
    },
    {
        "SongID": 728903,
        "Position": 198
    },
    {
        "SongID": 730381,
        "Position": 20
    },
    {
        "SongID": 753666,
        "Position": 52
    },
    {
        "SongID": 753725,
        "Position": 125
    },
    {
        "SongID": 947369,
        "Position": 1
    },
    {
        "SongID": 947370,
        "Position": 4
    },
    {
        "SongID": 947371,
        "Position": 8
    },
    {
        "SongID": 947372,
        "Position": 7
    },
    {
        "SongID": 947373,
        "Position": 24
    },
    {
        "SongID": 947374,
        "Position": 13
    },
    {
        "SongID": 947375,
        "Position": 2
    },
    {
        "SongID": 947376,
        "Position": 14
    },
    {
        "SongID": 947377,
        "Position": 37
    },
    {
        "SongID": 947378,
        "Position": 44
    },
    {
        "SongID": 947379,
        "Position": 32
    },
    {
        "SongID": 947380,
        "Position": 6
    },
    {
        "SongID": 947381,
        "Position": 39
    },
    {
        "SongID": 947382,
        "Position": 93
    },
    {
        "SongID": 947383,
        "Position": 47
    },
    {
        "SongID": 972340,
        "Position": 197
    },
    {
        "SongID": 972705,
        "Position": 85
    },
    {
        "SongID": 972707,
        "Position": 65
    },
    {
        "SongID": 975107,
        "Position": 33
    },
    {
        "SongID": 975183,
        "Position": 113
    },
    {
        "SongID": 975298,
        "Position": 81
    },
    {
        "SongID": 999542,
        "Position": 60
    },
    {
        "SongID": 999932,
        "Position": 190
    },
    {
        "SongID": 999946,
        "Position": 67
    }
]